{
    "0": "none",
    "1": "hide",
    "2": "bone",
    "3": "brick",
    "4": "cardboard",
    "5": "carpet",
    "6": "ceilingtile",
    "7": "ceramic",
    "8": "chalkboard",
    "9": "clutter",
    "10": "concrete",
    "11": "cork",
    "12": "engineeredstone",
    "13": "fabric",
    "14": "fiberglass",
    "15": "fire",
    "16": "foliage",
    "17": "food",
    "18": "fur",
    "19": "gemstone",
    "20": "glass",
    "21": "hair",
    "22": "icannottell",
    "23": "ice",
    "24": "leather",
    "25": "liquid",
    "26": "metal",
    "27": "mirror",
    "28": "notonlist",
    "29": "paint",
    "30": "paper",
    "31": "pearl",
    "32": "photograph",
    "33": "clearplastic",
    "34": "plastic",
    "35": "rubber",
    "36": "sand",
    "37": "skin",
    "38": "sky",
    "39": "snow",
    "40": "soap",
    "41": "soil",
    "42": "sponge",
    "43": "stone",
    "44": "polishedstone",
    "45": "styrofoam",
    "46": "tile",
    "47": "wallpaper",
    "48": "water",
    "49": "wax",
    "50": "whiteboard",
    "51": "wicker",
    "52": "wood",
    "53": "treewood",
    "54": "badpolygon",
    "55": "multiplematerials",
    "56": "asphalt"
}